androidkit/__init__.py
androidkit/apk/__init__.py
androidkit/apk/sources/__init__.py
androidkit/apk/sources/apkpure.py
androidkit/apk/sources/base.py
androidkit-0.1.2.dist-info/METADATA
androidkit-0.1.2.dist-info/WHEEL
androidkit-0.1.2.dist-info/top_level.txt
androidkit-0.1.2.dist-info/RECORD
