Metadata-Version: 2.4
Name: androidkit
Version: 0.1.2
Summary: Swiss army knife library for interacting with android things
Author: Leo Feradero Nugraha
Author-email: Leo Feradero Nugraha <leoferaderonugraha@gmail.com>
Keywords: android,apk
Classifier: Programming Language :: Python :: 3.11
Classifier: License :: OSI Approved :: GNU General Public License v3 (GPLv3)
Classifier: Topic :: Software Development :: Libraries
Requires-Python: >=3.11
Requires-Dist: requests>=2.32.4
Requires-Dist: selectolax>=0.4.4
Dynamic: author
Dynamic: requires-python
